{"index":{"links":{"/":[{"source":"/","target":"/notes/why","text":"Why do we meet?"},{"source":"/","target":"/notes/calendar","text":"When do we meet?"},{"source":"/","target":"/notes/meetings","text":"What to expect?"},{"source":"/","target":"/notes/calendar","text":"Attend the next meetup"}],"/notes/calendar":[{"source":"/notes/calendar","target":"/12032022","text":"Cyber Security, Safety, \u0026 Privacy"}]},"backlinks":{"/12032022":[{"source":"/notes/calendar","target":"/12032022","text":"Cyber Security, Safety, \u0026 Privacy"}],"/notes/calendar":[{"source":"/","target":"/notes/calendar","text":"When do we meet?"},{"source":"/","target":"/notes/calendar","text":"Attend the next meetup"}],"/notes/meetings":[{"source":"/","target":"/notes/meetings","text":"What to expect?"}],"/notes/why":[{"source":"/","target":"/notes/why","text":"Why do we meet?"}]}},"links":[{"source":"/","target":"/notes/why","text":"Why do we meet?"},{"source":"/","target":"/notes/calendar","text":"When do we meet?"},{"source":"/","target":"/notes/meetings","text":"What to expect?"},{"source":"/","target":"/notes/calendar","text":"Attend the next meetup"},{"source":"/notes/calendar","target":"/12032022","text":"Cyber Security, Safety, \u0026 Privacy"}]}